{
  "colors": {
    "default": {
      "theme_color": {
        "primary": "#00754D",
        "secondary": "#00A672",
        "tertiary": "#5DA9E9",
        "body": "#fff",
        "border": "#D9E2EC",
        "light": "#F5F7FA"
          
      },
      "text_color": {
        "text": "#000000",
        "text-dark": "#000000",
        "text-light": "#fff"
      }
    }
  },
  "fonts": {
    "font_family": {
      "primary": "Inter:wght@400;500;600",
      "primary_type": "Inter-Medium, Inter Placeholder, sans-serif",
      "secondary": "Inter:wght@400;500;600",
      "secondary_type": "Inter-Medium, Inter Placeholder, sans-serif"
    },
    "font_size": { "base": "16", "scale": "1.185" }
  }
}
